provider_variant_aarch64/__init__.py
provider_variant_aarch64/plugin.py
provider_variant_aarch64/vendor/__init__.py
provider_variant_aarch64/vendor/archspec/.git
provider_variant_aarch64/vendor/archspec/.gitignore
provider_variant_aarch64/vendor/archspec/.gitmodules
provider_variant_aarch64/vendor/archspec/.readthedocs.yml
provider_variant_aarch64/vendor/archspec/CITATION.cff
provider_variant_aarch64/vendor/archspec/COPYRIGHT
provider_variant_aarch64/vendor/archspec/Dockerfile
provider_variant_aarch64/vendor/archspec/LICENSE-APACHE
provider_variant_aarch64/vendor/archspec/LICENSE-MIT
provider_variant_aarch64/vendor/archspec/NOTICE
provider_variant_aarch64/vendor/archspec/README.md
provider_variant_aarch64/vendor/archspec/pyproject.toml
provider_variant_aarch64/vendor/archspec/tox.ini
provider_variant_aarch64/vendor/archspec/.github/dependabot.yml
provider_variant_aarch64/vendor/archspec/.github/workflows/codeql-analysis.yml
provider_variant_aarch64/vendor/archspec/.github/workflows/unit_tests.yml
provider_variant_aarch64/vendor/archspec/archspec/__init__.py
provider_variant_aarch64/vendor/archspec/archspec/__main__.py
provider_variant_aarch64/vendor/archspec/archspec/cli.py
provider_variant_aarch64/vendor/archspec/archspec/cpu/__init__.py
provider_variant_aarch64/vendor/archspec/archspec/cpu/alias.py
provider_variant_aarch64/vendor/archspec/archspec/cpu/detect.py
provider_variant_aarch64/vendor/archspec/archspec/cpu/microarchitecture.py
provider_variant_aarch64/vendor/archspec/archspec/cpu/schema.py
provider_variant_aarch64/vendor/archspec/archspec/json/.git
provider_variant_aarch64/vendor/archspec/archspec/json/COPYRIGHT
provider_variant_aarch64/vendor/archspec/archspec/json/LICENSE-APACHE
provider_variant_aarch64/vendor/archspec/archspec/json/LICENSE-MIT
provider_variant_aarch64/vendor/archspec/archspec/json/NOTICE
provider_variant_aarch64/vendor/archspec/archspec/json/README.md
provider_variant_aarch64/vendor/archspec/archspec/json/.github/dependabot.yml
provider_variant_aarch64-0.0.1.post2.dist-info/entry_points.txt
provider_variant_aarch64-0.0.1.post2.dist-info/licenses/LICENSE
provider_variant_aarch64-0.0.1.post2.dist-info/WHEEL
provider_variant_aarch64-0.0.1.post2.dist-info/METADATA
provider_variant_aarch64-0.0.1.post2.dist-info/RECORD
